{
    "data": {
        "user": {
            "id": "1"
        },
        "expenses": [
            {
                "id": "1",
                "description": "Groceries",
                "amount": "50.00",
                "date": "2024-02-01"
            },
            {
                "id": "2",
                "description": "Dinner",
                "amount": "30.00",
                "date": "2024-01-30"
            }
        ],
        "income": [
            {
                "id": "3",
                "source": "Salary",
                "amount": "5000.00",
                "date": "2024-02-01"
            },
            {
                "id": "4",
                "source": "Tips",
                "amount": "50.00",
                "date": "2024-02-01"
            }
        ]
    }
}